{
    "fluentMethods": true,
    "relationships": [],
    "fields": [
        {
            "fieldName": "nombre",
            "fieldType": "String",
            "fieldValidateRules": [
                "required"
            ]
        },
        {
            "fieldName": "briefDescription",
            "fieldType": "String",
            "fieldValidateRules": [
                "required"
            ]
        },
        {
            "fieldName": "description",
            "fieldType": "byte[]",
            "fieldTypeBlobContent": "text",
            "fieldValidateRules": [
                "required"
            ]
        },
        {
            "fieldName": "order",
            "fieldType": "Integer"
        }
    ],
    "changelogDate": "20170804215617",
    "entityTableName": "report_indicator",
    "dto": "no",
    "pagination": "pagination",
    "service": "serviceImpl"
}